<?xml version="1.0" encoding="UTF-8"?>
<ti:work xmlns:ti="http://chs.harvard.edu/xmlns/cts" groupUrn="urn:cts:greekLit:tlg0004" projid="greekLit:tlg0004" urn="urn:cts:greekLit:tlg0004.tlg001" xml:lang="grc">
  <ti:title xml:lang="eng">Vitae philosophorum</ti:title>
  <ti:author xml:lang="eng">Diogenes Laertius</ti:author>
  <ti:edition urn="urn:cts:greekLit:tlg0004.tlg001.agdtm-grc1" workUrn="urn:cts:greekLit:tlg0004.tlg001" xml:lang="grc">
    <ti:editor xml:lang="eng">placeholder</ti:editor>
    <ti:label xml:lang="eng">Diogenes Laertius, Vitae philosophorum</ti:label>
    <ti:description xml:lang="eng">Diogenes Laertius, Vitae philosophorum</ti:description>
  </ti:edition>
</ti:work>